jaxnet/__init__.py
jaxnet/core.py
jaxnet/modules.py
jaxnet/optimizers.py
jaxnet-0.2.7.dist-info/LICENSE
jaxnet-0.2.7.dist-info/METADATA
jaxnet-0.2.7.dist-info/WHEEL
jaxnet-0.2.7.dist-info/top_level.txt
jaxnet-0.2.7.dist-info/RECORD
