Metadata-Version: 2.1
Name: jaxnet
Version: 0.2.7
Summary: Neural Nets for JAX
Home-page: http://github.com/JuliusKunze/jaxnet
License: UNKNOWN
Platform: UNKNOWN
Classifier: Programming Language :: Python :: 3
Classifier: License :: OSI Approved :: Apache Software License
Classifier: Topic :: Scientific/Engineering :: Artificial Intelligence
Classifier: Intended Audience :: Developers
Classifier: Intended Audience :: Education
Classifier: Intended Audience :: Science/Research
Requires-Python: >=3.6
Requires-Dist: jax (>=0.1.42)
Requires-Dist: dill
